xmldiffs/__init__.py
xmldiffs/command_line.py
xmldiffs-0.0.4.dist-info/LICENSE
xmldiffs-0.0.4.dist-info/METADATA
xmldiffs-0.0.4.dist-info/WHEEL
xmldiffs-0.0.4.dist-info/entry_points.txt
xmldiffs-0.0.4.dist-info/top_level.txt
xmldiffs-0.0.4.dist-info/RECORD
